[
    {
        "title": "La participation aux forums de TripAdvisor est-elle payante ?",
        "content": "Non, c'est entièrement gratuit."
    },
    {
        "title": "Allez-vous vendre mon nom ?",
        "content": "Non, en aucune façon ! Nous sommes contre le spam"
    },
    {
        "title": "Suis-je obligé de m'inscrire ?",
        "content": "Il n'est pas nécessaire de s'inscrire pour consulter les messages."
    },
    {
        "title": "Puis-je publier des images ?",
        "content": "Les voyageurs n'ont malheureusement pas la possibilité de publier des images dans leurs messages."
    }
]